client/__init__.py
client/client.py
endpoint_api_client-0.0.2.dist-info/METADATA
endpoint_api_client-0.0.2.dist-info/WHEEL
endpoint_api_client-0.0.2.dist-info/top_level.txt
endpoint_api_client-0.0.2.dist-info/RECORD
