Metadata-Version: 2.1
Name: endpoint-api-client
Version: 0.0.2
Summary: This module implements API-client to storage-endpoint
Home-page: https://github.com/galavasteg/api_client
Author: Artem Shakurov
Author-email: galavasteg@gmail.com
License: UNKNOWN
Platform: UNKNOWN
Classifier: Programming Language :: Python :: 3.8
Classifier: Programming Language :: Python :: 3.7
Classifier: Operating System :: OS Independent
Requires-Dist: requests (==2.23.0)
